{
  "sections": {
    "hero": {
      "type": "hero",
      "settings": {
        "background": "shopify:\/\/shop_images\/hero_bg.jpg",
        "background_webp": "shopify:\/\/shop_images\/hero_bg.webp",
        "decor_1": "shopify:\/\/shop_images\/decor_1.png",
        "decor_1_webp": "shopify:\/\/shop_images\/decor_1.webp",
        "decor_2": "shopify:\/\/shop_images\/decor_2.png",
        "decor_2_webp": "shopify:\/\/shop_images\/decor_2.webp",
        "hero_main": "shopify:\/\/shop_images\/hero.png",
        "hero_main_webp": "shopify:\/\/shop_images\/hero.webp",
        "hero_logo": "shopify:\/\/shop_images\/Logo.png",
        "hero_logo_webp": "shopify:\/\/shop_images\/Logo.webp"
      }
    }
  },
  "order": [
    "hero"
  ]
}